setup.py
discum/RESTapiwrap.py
discum/__init__.py
discum/__version__.py
discum/discum.py
discum/logger.py
discum/gateway/__init__.py
discum/gateway/event.py
discum/gateway/gateway.py
discum/gateway/parse.py
discum/gateway/request.py
discum/gateway/response.py
discum/gateway/session.py
discum/gateway/types.py
discum/gateway/channels/__init__.py
discum/gateway/channels/parse.py
discum/gateway/dms/__init__.py
discum/gateway/dms/request.py
discum/gateway/guild/__init__.py
discum/gateway/guild/combo.py
discum/gateway/guild/parse.py
discum/gateway/guild/request.py
discum/gateway/media/__init__.py
discum/gateway/media/request.py
discum/gateway/messages/__init__.py
discum/gateway/messages/parse.py
discum/gateway/start/__init__.py
discum/gateway/start/parse.py
discum/gateway/user/__init__.py
discum/gateway/user/combo.py
discum/gateway/user/parse.py
discum/gateway/user/request.py
discum/guild/__init__.py
discum/guild/guild.py
discum/messages/__init__.py
discum/messages/messages.py
discum/science/__init__.py
discum/science/science.py
discum/start/__init__.py
discum/start/login.py
discum/start/other.py
discum/start/superproperties.py
discum/stickers/__init__.py
discum/stickers/stickers.py
discum/user/__init__.py
discum/user/user.py
discum/utils/__init__.py
discum/utils/accessibility.py
discum/utils/client_uuid.py
discum/utils/color.py
discum/utils/contextproperties.py
discum/utils/embed.py
discum/utils/fileparse.py
discum/utils/permissions.py
discum/utils/totp.py
discumlukyy.egg-info/PKG-INFO
discumlukyy.egg-info/SOURCES.txt
discumlukyy.egg-info/dependency_links.txt
discumlukyy.egg-info/requires.txt
discumlukyy.egg-info/top_level.txt